faster_sentiment/__init__.py
faster_sentiment/cli.py
faster_sentiment/faster_sentiment.py
faster_sentiment/utils/__init__.py
faster_sentiment/utils/example.py
faster_sentiment/utils/tools.py
faster_sentiment-0.1.0.dist-info/AUTHORS.rst
faster_sentiment-0.1.0.dist-info/LICENSE
faster_sentiment-0.1.0.dist-info/METADATA
faster_sentiment-0.1.0.dist-info/WHEEL
faster_sentiment-0.1.0.dist-info/entry_points.txt
faster_sentiment-0.1.0.dist-info/top_level.txt
faster_sentiment-0.1.0.dist-info/RECORD
